[{"name":"/mobile","nodes":[{"id":"4343fb64-c581-b24a-7f21-d7a25f0e4590","type":"Page","parameters":{"title":"portrait"},"ports":[],"children":[{"id":"ef1af1fd-e4a1-1ec8-a27c-c454cf842d43","type":"Group","parameters":{"position":"absolute","sizeMode":"explicit","width":{"value":100,"unit":"%","isFixed":false},"height":{"value":100,"unit":"%","isFixed":false}},"ports":[],"children":[{"id":"b439c4a8-3166-65c2-0683-5de748f1fb58","type":"/about","parameters":{},"ports":[],"children":[]},{"id":"896ad7aa-c367-4b2e-ebc0-ff4a7337a754","type":"Group","parameters":{"width":{"value":100,"unit":"%","isFixed":false},"height":{"value":100,"unit":"%","isFixed":false},"position":"relative","alignX":"right","clip":true,"borderRadius":{"value":20,"unit":"px"},"marginLeft":{"value":10,"unit":"px"},"marginTop":{"value":10,"unit":"px"},"marginRight":{"value":10,"unit":"px"},"boxShadowEnabled":true,"boxShadowSpreadRadius":{"value":0,"unit":"px"},"boxShadowOffsetY":{"value":0,"unit":"px"},"boxShadowBlurRadius":{"value":10,"unit":"px"},"boxShadowInset":false,"boxShadowColor":"Grey - 400","paddingBottom":{"value":0,"unit":"px"},"marginBottom":{"value":10,"unit":"px"},"sizeMode":"explicit"},"ports":[],"children":[{"id":"9c679d14-35bd-d90c-e50c-adca14be7e88","type":"/Map Layer","parameters":{},"ports":[],"children":[]}]},{"id":"20bf7097-a203-8145-9645-7c3ee285a958","type":"Group","parameters":{"width":{"value":100,"unit":"%"},"zIndex":2,"marginTop":{"value":0,"unit":"px"},"borderRadius":{"value":20,"unit":"px"},"boxShadowEnabled":true,"boxShadowOffsetY":{"value":0,"unit":"px"},"boxShadowBlurRadius":{"value":8,"unit":"px"},"boxShadowSpreadRadius":{"value":0,"unit":"px"},"sizeMode":"contentHeight","flexDirection":"column","position":"relative","marginBottom":{"value":10,"unit":"px"},"marginRight":{"value":10,"unit":"px"},"marginLeft":{"value":10,"unit":"px"},"height":{"value":30,"unit":"%","isFixed":false},"justifyContent":"flex-end","alignY":"bottom","backgroundColor":"White","boxShadowColor":"Grey - 400"},"ports":[],"children":[{"id":"9d932cdb-70fa-b1f6-f598-df58c0e534e4","type":"Group","parameters":{"height":{"value":22,"unit":"px"}},"ports":[],"children":[{"id":"bb34efbb-e2f1-f3d0-0bbd-af526ac1ab5f","type":"Group","parameters":{"height":{"value":4,"unit":"px"},"width":{"value":30,"unit":"px"},"alignX":"center","marginTop":{"value":10,"unit":"px"},"backgroundColor":"Grey - 300","borderRadius":{"value":20,"unit":"px"},"clip":true},"ports":[],"children":[]}]},{"id":"9017bd93-d3e0-8413-0984-62ef2c238c86","type":"Group","parameters":{"flexDirection":"row","sizeMode":"contentHeight"},"ports":[],"children":[{"id":"a86ca009-482c-ef21-4b5a-2f985e3f198a","type":"Group","parameters":{"width":{"value":50,"unit":"%","isFixed":false},"sizeMode":"explicit","height":{"value":100,"unit":"px","isFixed":false},"marginRight":{"value":12,"unit":"px"},"backgroundColor":"White","borderRadius":{"value":20,"unit":"px"},"clip":true,"boxShadowEnabled":false,"boxShadowBlurRadius":{"value":10,"unit":"px"},"boxShadowSpreadRadius":{"value":0,"unit":"px"},"boxShadowColor":"Grey - 300"},"ports":[],"children":[{"id":"89956ddb-db95-d631-e094-d6dc191359cd","type":"/Info Layer","parameters":{"width":{"value":30,"unit":"%"}},"ports":[],"children":[]}]},{"id":"47918cff-9106-2cb7-aff3-2f573a7408d6","type":"Group","parameters":{"height":{"value":100,"unit":"px"},"width":{"value":50,"unit":"%"},"marginRight":{"value":20,"unit":"px"}},"ports":[],"children":[{"id":"7be4c2a0-099d-33d7-6185-d0937a5a361d","type":"/Info Layer/image","parameters":{},"ports":[],"children":[]}]}]},{"id":"85c271b1-42e8-673a-0a11-b4978f3f6a0e","type":"Group","parameters":{"width":{"value":100,"unit":"%","isFixed":true},"sizeMode":"explicit","height":{"value":5,"unit":"px","isFixed":false},"paddingLeft":{"value":12,"unit":"px"},"paddingRight":{"value":12,"unit":"px"},"alignY":"bottom","position":"relative","marginTop":{"value":10,"unit":"px"},"borderRadius":{"value":20,"unit":"px"},"scrollEnabled":true,"boxShadowEnabled":false,"boxShadowBlurRadius":{"value":10,"unit":"px"},"boxShadowSpreadRadius":{"value":0,"unit":"px"},"boxShadowColor":"Grey - 300","mounted":true,"clip":true},"ports":[],"children":[{"id":"d944c5b8-6f72-542f-d9a1-8ef5b3a194f4","type":"Text","parameters":{"fontFamily":"fonts/HelveticaNowText-Light.ttf","sizeMode":"contentHeight","text":"","color":"Grey - 600","marginTop":{"value":0,"unit":"px"},"wordBreak":"normal","fontSize":{"value":16,"unit":"px"},"position":"absolute","marginLeft":{"value":12,"unit":"px"},"marginBottom":{"value":12,"unit":"px"},"marginRight":{"value":12,"unit":"px"}},"ports":[],"children":[]}]}]}]}]},{"id":"4340a11c-ccf9-762b-7a6f-c7747f9c73e5","type":"DbCollection2","parameters":{"collectionName":"city","storageEnableLimit":true,"storageLimit":100},"ports":[],"children":[]},{"id":"086ec24f-4f95-8523-e915-16ce97762233","type":"DbCollection2","parameters":{"collectionName":"city","storageEnableLimit":true,"storageLimit":100,"storageSkip":100},"ports":[],"children":[]},{"id":"bd923b3d-642c-095c-0710-0ea8d5fb7339","type":"DbCollection2","parameters":{"collectionName":"city","storageEnableLimit":true,"storageLimit":100,"storageSkip":200},"ports":[],"children":[]},{"id":"2be587d7-6df3-9432-4710-4e471270d7db","type":"JavaScriptFunction","parameters":{"functionScript":"var a = Inputs.a;\nvar b = Inputs.b;\nvar c = Inputs.c;\nvar d = Inputs.d; \n\nOutputs.result = a.concat(b, c, d);"},"ports":[{"name":"in-a","displayName":"a","plug":"input","type":"*","group":"Inputs","index":4},{"name":"in-b","displayName":"b","plug":"input","type":"*","group":"Inputs","index":5},{"name":"in-c","displayName":"c","plug":"input","type":"*","group":"Inputs","index":6},{"name":"in-d","displayName":"d","plug":"input","type":"*","group":"Inputs","index":7},{"name":"out-result","displayName":"result","plug":"output","type":"*","group":"Outputs","index":8}],"children":[]},{"id":"632119cd-e5d4-08d9-e3cd-0796ba97cff3","type":"DbCollection2","parameters":{"collectionName":"city","storageEnableLimit":true,"storageLimit":100,"storageSkip":300},"ports":[],"children":[]},{"id":"b53cda65-f4fb-800a-2c59-e7c201a0659b","type":"States","parameters":{"states":"closed,open","values":"height,show_icon","value-closed-height":5,"value-open-height":200,"type-show_icon":"boolean","value-closed-show_icon":true},"ports":[],"children":[]},{"id":"d2e659af-3e53-9901-7d81-078290c601e0","type":"JavaScriptFunction","parameters":{"functionScript":"let touchStartY;\nlet touchEndY;\n\nfunction handleTouchStart(event) {\n  // Get the height of the window\n  const windowHeight = window.innerHeight;\n\n  // Check if the touch event starts within the bottom 100px of the screen\n  if (event.touches[0].clientY > windowHeight - 400) {\n    touchStartY = event.touches[0].clientY;\n  }\n}\n\nfunction handleTouchEnd(event) {\n  if (touchStartY) {\n    touchEndY = event.changedTouches[0].clientY;\n    handleSwipe();\n  }\n\n  // Reset touchStartY to ensure the next swipe also starts within the bottom 100px\n  touchStartY = null;\n}\n\nfunction handleSwipe() {\n  if (touchEndY < touchStartY) {\n    console.log(\"Swiped up\");\n    Outputs.SwipeUP();\n    // Your code here to execute when a swipe up is detected\n  } else if (touchEndY > touchStartY) {\n    console.log(\"Swiped down\");\n    Outputs.SwipeDown();\n    // Your code here to execute when a swipe down is detected\n  }\n}\n\n// Add event listeners for touchstart and touchend events\ndocument.addEventListener('touchstart', handleTouchStart, false);\ndocument.addEventListener('touchend', handleTouchEnd, false);\n\n\n\n"},"ports":[{"name":"out-SwipeUP","displayName":"SwipeUP","plug":"output","type":"signal","group":"Outputs","index":4},{"name":"out-SwipeDown","displayName":"SwipeDown","plug":"output","type":"signal","group":"Outputs","index":5}],"children":[]},{"id":"76e6819d-49c4-4c43-1bef-5afd1e6bf904","type":"States","parameters":{"states":"hidden,visible","values":"opacity","value-hidden-opacity":0,"value-visible-opacity":1,"transitiondef-visible":{"curve":[0,0,1,1],"dur":1500,"delay":500},"transitiondef-hidden":{"curve":[0,0,1,1],"dur":1500,"delay":500},"transition-visible-opacity":{"curve":[0,0,1,1],"dur":1000,"delay":300}},"ports":[],"children":[]},{"id":"6362cd11-a80b-35a3-a0f9-9c52bb92e86b","type":"JavaScriptFunction","parameters":{"functionScript":"function getScreenOrientation() {\n  if (window.innerWidth > window.innerHeight) {\n    Outputs.landscape();\n  } else {\n    if (window.innerWidth < 550) {\n      Outputs.mobile();\n    }else{\n      Outputs.portrait();\n    }\n    \n  }\n}\n\nfunction onWindowResize() {\n  getScreenOrientation();\n}\n\n// Listen for window resize events\nwindow.addEventListener('resize', onWindowResize);\n\n// Call the function initially to get the current orientation and check the window width\nonWindowResize();"},"ports":[{"name":"out-landscape","displayName":"landscape","plug":"output","type":"signal","group":"Outputs","index":4},{"name":"out-mobile","displayName":"mobile","plug":"output","type":"signal","group":"Outputs","index":5},{"name":"out-portrait","displayName":"portrait","plug":"output","type":"signal","group":"Outputs","index":6}],"children":[]},{"id":"7553fb27-9015-6a51-ffea-7bc80a24efd4","type":"RouterNavigate","parameters":{"router":"Main","target":"/portrait"},"ports":[],"children":[]},{"id":"f7cf275c-4697-6e38-aba7-5ab78350c77d","type":"RouterNavigate","parameters":{"router":"Main","target":"/landscape"},"ports":[],"children":[]}],"connections":[{"sourceId":"9c679d14-35bd-d90c-e50c-adca14be7e88","sourcePort":"city","targetId":"89956ddb-db95-d631-e094-d6dc191359cd","targetPort":"city"},{"sourceId":"9c679d14-35bd-d90c-e50c-adca14be7e88","sourcePort":"why","targetId":"89956ddb-db95-d631-e094-d6dc191359cd","targetPort":"why"},{"sourceId":"9c679d14-35bd-d90c-e50c-adca14be7e88","sourcePort":"image","targetId":"89956ddb-db95-d631-e094-d6dc191359cd","targetPort":"image"},{"sourceId":"9c679d14-35bd-d90c-e50c-adca14be7e88","sourcePort":"material","targetId":"89956ddb-db95-d631-e094-d6dc191359cd","targetPort":"material"},{"sourceId":"9c679d14-35bd-d90c-e50c-adca14be7e88","sourcePort":"lng","targetId":"89956ddb-db95-d631-e094-d6dc191359cd","targetPort":"lng"},{"sourceId":"9c679d14-35bd-d90c-e50c-adca14be7e88","sourcePort":"lat","targetId":"89956ddb-db95-d631-e094-d6dc191359cd","targetPort":"lat"},{"sourceId":"9c679d14-35bd-d90c-e50c-adca14be7e88","sourcePort":"adress","targetId":"89956ddb-db95-d631-e094-d6dc191359cd","targetPort":"adress"},{"sourceId":"9c679d14-35bd-d90c-e50c-adca14be7e88","sourcePort":"image","targetId":"7be4c2a0-099d-33d7-6185-d0937a5a361d","targetPort":"img"},{"sourceId":"4340a11c-ccf9-762b-7a6f-c7747f9c73e5","sourcePort":"fetched","targetId":"086ec24f-4f95-8523-e915-16ce97762233","targetPort":"storageFetch"},{"sourceId":"086ec24f-4f95-8523-e915-16ce97762233","sourcePort":"fetched","targetId":"bd923b3d-642c-095c-0710-0ea8d5fb7339","targetPort":"storageFetch"},{"sourceId":"4340a11c-ccf9-762b-7a6f-c7747f9c73e5","sourcePort":"items","targetId":"2be587d7-6df3-9432-4710-4e471270d7db","targetPort":"in-a"},{"sourceId":"086ec24f-4f95-8523-e915-16ce97762233","sourcePort":"items","targetId":"2be587d7-6df3-9432-4710-4e471270d7db","targetPort":"in-b"},{"sourceId":"bd923b3d-642c-095c-0710-0ea8d5fb7339","sourcePort":"items","targetId":"2be587d7-6df3-9432-4710-4e471270d7db","targetPort":"in-c"},{"sourceId":"bd923b3d-642c-095c-0710-0ea8d5fb7339","sourcePort":"fetched","targetId":"632119cd-e5d4-08d9-e3cd-0796ba97cff3","targetPort":"storageFetch"},{"sourceId":"632119cd-e5d4-08d9-e3cd-0796ba97cff3","sourcePort":"items","targetId":"2be587d7-6df3-9432-4710-4e471270d7db","targetPort":"in-d"},{"sourceId":"632119cd-e5d4-08d9-e3cd-0796ba97cff3","sourcePort":"fetched","targetId":"2be587d7-6df3-9432-4710-4e471270d7db","targetPort":"run"},{"sourceId":"2be587d7-6df3-9432-4710-4e471270d7db","sourcePort":"out-result","targetId":"9c679d14-35bd-d90c-e50c-adca14be7e88","targetPort":"items"},{"sourceId":"89956ddb-db95-d631-e094-d6dc191359cd","sourcePort":"text","targetId":"d944c5b8-6f72-542f-d9a1-8ef5b3a194f4","targetPort":"text"},{"sourceId":"47918cff-9106-2cb7-aff3-2f573a7408d6","sourcePort":"boundingWidth","targetId":"a86ca009-482c-ef21-4b5a-2f985e3f198a","targetPort":"height"},{"sourceId":"b53cda65-f4fb-800a-2c59-e7c201a0659b","sourcePort":"height","targetId":"85c271b1-42e8-673a-0a11-b4978f3f6a0e","targetPort":"height"},{"sourceId":"d2e659af-3e53-9901-7d81-078290c601e0","sourcePort":"out-SwipeUP","targetId":"b53cda65-f4fb-800a-2c59-e7c201a0659b","targetPort":"to-open"},{"sourceId":"d2e659af-3e53-9901-7d81-078290c601e0","sourcePort":"out-SwipeDown","targetId":"b53cda65-f4fb-800a-2c59-e7c201a0659b","targetPort":"to-closed"},{"sourceId":"20bf7097-a203-8145-9645-7c3ee285a958","sourcePort":"onClick","targetId":"b53cda65-f4fb-800a-2c59-e7c201a0659b","targetPort":"toggle"},{"sourceId":"ef1af1fd-e4a1-1ec8-a27c-c454cf842d43","sourcePort":"didMount","targetId":"76e6819d-49c4-4c43-1bef-5afd1e6bf904","targetPort":"to-visible"},{"sourceId":"76e6819d-49c4-4c43-1bef-5afd1e6bf904","sourcePort":"opacity","targetId":"ef1af1fd-e4a1-1ec8-a27c-c454cf842d43","targetPort":"opacity"},{"sourceId":"6362cd11-a80b-35a3-a0f9-9c52bb92e86b","sourcePort":"out-portrait","targetId":"7553fb27-9015-6a51-ffea-7bc80a24efd4","targetPort":"navigate"},{"sourceId":"6362cd11-a80b-35a3-a0f9-9c52bb92e86b","sourcePort":"out-landscape","targetId":"f7cf275c-4697-6e38-aba7-5ab78350c77d","targetPort":"navigate"},{"sourceId":"ef1af1fd-e4a1-1ec8-a27c-c454cf842d43","sourcePort":"didMount","targetId":"6362cd11-a80b-35a3-a0f9-9c52bb92e86b","targetPort":"run"}],"ports":[],"roots":["4343fb64-c581-b24a-7f21-d7a25f0e4590"]}]